setup.py
olympus/__init__.py
olympus/eval_report.py
olympus/eval_report_test.py
olympus/eval_task.py
olympus/eval_task_test.py
olympus/model.py
olympus/model_test.py
olympus/utils.py
olympus_bat/__init__.py
olympus_bat/eval_report.py
olympus_bat/eval_report_test.py
olympus_bat/eval_task.py
olympus_bat/eval_task_test.py
olympus_bat/model.py
olympus_bat/model_test.py
olympus_bat/utils.py
olympusx.egg-info/PKG-INFO
olympusx.egg-info/SOURCES.txt
olympusx.egg-info/dependency_links.txt
olympusx.egg-info/requires.txt
olympusx.egg-info/top_level.txt