Metadata-Version: 1.0
Name: olympusx
Version: 1.0.2
Summary: an api of project olympus
Home-page: https://github.com/gggggaoyu/olympus
Author: gaoyu
Author-email: xiangqukk@163.com
License: SMO Licence
Keywords: pip,olympus,ffffff
Platform: any
